{"title":"尺取法","date":"2018-01-07T16:00:00.000Z","author":"luoyayu","excerpt":"<p>尺取法顾名思义是用尺子一段一段测量。测量物件长度通常是一端对其，看另一端的刻度得出答案；<br>借挑战上的话 尺取法通常是数组保存一对下标，即所选取的区间的左右端点，然后根据实际问题不断推进区间，在这其中可以根据已有经验保持右端点从上一状态继续推进。</p>\n<p>虽然比较暴力，但往往很高效，可以优化普通枚举区间到<code>O(n)</code>时间。遂在此总结下。<br>","slug":"2018-01-08-尺取法小结","comments":true,"tags":["ACM-尺取法","ACM-技巧","ACM-总结"],"categories":["ACM"],"updated":"2018-08-25T02:48:28.000Z","content":"<p>尺取法顾名思义是用尺子一段一段测量。测量物件长度通常是一端对其，看另一端的刻度得出答案；<br>借挑战上的话 尺取法通常是数组保存一对下标，即所选取的区间的左右端点，然后根据实际问题不断推进区间，在这其中可以根据已有经验保持右端点从上一状态继续推进。</p>\n<p>虽然比较暴力，但往往很高效，可以优化普通枚举区间到<code>O(n)</code>时间。遂在此总结下。<br><a id=\"more\"></a></p>\n<h1 id=\"POJ-3061-Sequence\"><a href=\"#POJ-3061-Sequence\" class=\"headerlink\" title=\"POJ 3061 Sequence\"></a>POJ 3061 Sequence</h1><h2 id=\"题意\"><a href=\"#题意\" class=\"headerlink\" title=\"题意\"></a>题意</h2><p>给出一个长度为$N(1e5)$的整数$(1e5)$序列,找出一段长度最小的区间满足区间元素和大于等于给定的$S(1e8)$</p>\n<h2 id=\"trick\"><a href=\"#trick\" class=\"headerlink\" title=\"trick\"></a>trick</h2><p>先固定好初始的长度，然后左端点享有移动一个单位，相应调整右端点，这样便能在<code>O(n)</code>取遍序列所有满足的情况。<br>第一次写的小贴士：找满足的右端点时<code>r++</code>,那么区间长度是<code>r-l</code>不需要额外加<code>1</code></p>\n<h2 id=\"code\"><a href=\"#code\" class=\"headerlink\" title=\"code\"></a>code</h2><figure class=\"highlight cpp\"><table><tr><td class=\"gutter\"><pre><span class=\"line\">1</span><br><span class=\"line\">2</span><br><span class=\"line\">3</span><br><span class=\"line\">4</span><br><span class=\"line\">5</span><br><span class=\"line\">6</span><br><span class=\"line\">7</span><br><span class=\"line\">8</span><br><span class=\"line\">9</span><br><span class=\"line\">10</span><br><span class=\"line\">11</span><br><span class=\"line\">12</span><br><span class=\"line\">13</span><br><span class=\"line\">14</span><br><span class=\"line\">15</span><br><span class=\"line\">16</span><br><span class=\"line\">17</span><br><span class=\"line\">18</span><br><span class=\"line\">19</span><br><span class=\"line\">20</span><br><span class=\"line\">21</span><br><span class=\"line\">22</span><br><span class=\"line\">23</span><br><span class=\"line\">24</span><br><span class=\"line\">25</span><br><span class=\"line\">26</span><br><span class=\"line\">27</span><br><span class=\"line\">28</span><br><span class=\"line\">29</span><br><span class=\"line\">30</span><br><span class=\"line\">31</span><br></pre></td><td class=\"code\"><pre><span class=\"line\"><span class=\"meta\">#<span class=\"meta-keyword\">include</span> <span class=\"meta-string\">&lt;cstdio&gt;</span></span></span><br><span class=\"line\"><span class=\"meta\">#<span class=\"meta-keyword\">include</span> <span class=\"meta-string\">&lt;algorithm&gt;</span></span></span><br><span class=\"line\"><span class=\"keyword\">using</span> <span class=\"keyword\">namespace</span> <span class=\"built_in\">std</span>;</span><br><span class=\"line\"><span class=\"keyword\">const</span> <span class=\"keyword\">int</span> maxn = <span class=\"number\">1e5</span>+<span class=\"number\">7</span>;</span><br><span class=\"line\"><span class=\"keyword\">int</span> a[maxn];</span><br><span class=\"line\"><span class=\"function\"><span class=\"keyword\">int</span> <span class=\"title\">main</span><span class=\"params\">()</span> </span>&#123;</span><br><span class=\"line\">    <span class=\"keyword\">int</span> t; <span class=\"built_in\">scanf</span>(<span class=\"string\">\"%d\"</span>, &amp;t);</span><br><span class=\"line\">    <span class=\"keyword\">while</span> (t--) &#123;</span><br><span class=\"line\">        <span class=\"keyword\">int</span> n, S, tot = <span class=\"number\">0</span>;</span><br><span class=\"line\">        <span class=\"built_in\">scanf</span>(<span class=\"string\">\"%d%d\"</span>, &amp;n, &amp;S);</span><br><span class=\"line\">        <span class=\"keyword\">for</span> (<span class=\"keyword\">int</span> i = <span class=\"number\">1</span>; i &lt;= n; i++) &#123;</span><br><span class=\"line\">            <span class=\"built_in\">scanf</span>(<span class=\"string\">\"%d\"</span>, &amp;a[i]);</span><br><span class=\"line\">            tot += a[i];</span><br><span class=\"line\">        &#125;</span><br><span class=\"line\">        <span class=\"keyword\">if</span> (tot &lt;= S) &#123;</span><br><span class=\"line\">            <span class=\"built_in\">printf</span>(<span class=\"string\">\"%d\\n\"</span>, tot == S ? n : <span class=\"number\">0</span>);</span><br><span class=\"line\">            <span class=\"keyword\">continue</span>;</span><br><span class=\"line\">        &#125;</span><br><span class=\"line\">        <span class=\"keyword\">int</span> l = <span class=\"number\">0</span>, r = <span class=\"number\">0</span>; <span class=\"comment\">//初始化尺子</span></span><br><span class=\"line\">        <span class=\"keyword\">int</span> sum = <span class=\"number\">0</span>; <span class=\"comment\">// 初始化尺子长度存的信息</span></span><br><span class=\"line\">        <span class=\"keyword\">int</span> res = n + <span class=\"number\">1</span>; <span class=\"comment\">//初始化答案inf=n+1</span></span><br><span class=\"line\">        <span class=\"keyword\">while</span> (<span class=\"number\">1</span>) &#123;<span class=\"comment\">// 尺子不断向右推直到从某个左端起最大能取到的和小于S</span></span><br><span class=\"line\">            <span class=\"keyword\">while</span> (r &lt;= n &amp;&amp; sum &lt; S) <span class=\"comment\">//推尺子右端到满足题意</span></span><br><span class=\"line\">                sum += a[r++];</span><br><span class=\"line\">            <span class=\"keyword\">if</span> (sum &lt; S) <span class=\"keyword\">break</span>;</span><br><span class=\"line\">            res = min(res, r - l); <span class=\"comment\">// r已经加过1</span></span><br><span class=\"line\">            sum -= a[l++]; <span class=\"comment\">//推尺子左端一格，同时更新sum</span></span><br><span class=\"line\">        &#125;</span><br><span class=\"line\">        <span class=\"built_in\">printf</span>(<span class=\"string\">\"%d\\n\"</span>, res &gt; n ? <span class=\"number\">0</span> : res);</span><br><span class=\"line\">    &#125;</span><br><span class=\"line\">&#125;</span><br></pre></td></tr></table></figure>\n<h1 id=\"HDU-5672-String\"><a href=\"#HDU-5672-String\" class=\"headerlink\" title=\"HDU 5672 String\"></a>HDU 5672 String</h1><h2 id=\"题意-1\"><a href=\"#题意-1\" class=\"headerlink\" title=\"题意\"></a>题意</h2><p>给出长度小于$1e6$的字符串，问有多少子串其中至少有$k$个不同的字母</p>\n<h2 id=\"trick-1\"><a href=\"#trick-1\" class=\"headerlink\" title=\"trick\"></a>trick</h2><p>考虑到现在的区间长度内的信息可以利用，当然是尺取一下：对于满足的串<code>[l,r]</code>, 其后的<code>len-r+1</code>当然都满足啦,<code>O(n)</code>即可</p>\n<h2 id=\"code-1\"><a href=\"#code-1\" class=\"headerlink\" title=\"code\"></a>code</h2><figure class=\"highlight cpp\"><table><tr><td class=\"gutter\"><pre><span class=\"line\">1</span><br><span class=\"line\">2</span><br><span class=\"line\">3</span><br><span class=\"line\">4</span><br><span class=\"line\">5</span><br><span class=\"line\">6</span><br><span class=\"line\">7</span><br><span class=\"line\">8</span><br><span class=\"line\">9</span><br><span class=\"line\">10</span><br><span class=\"line\">11</span><br><span class=\"line\">12</span><br><span class=\"line\">13</span><br><span class=\"line\">14</span><br><span class=\"line\">15</span><br><span class=\"line\">16</span><br><span class=\"line\">17</span><br><span class=\"line\">18</span><br><span class=\"line\">19</span><br><span class=\"line\">20</span><br><span class=\"line\">21</span><br><span class=\"line\">22</span><br><span class=\"line\">23</span><br><span class=\"line\">24</span><br><span class=\"line\">25</span><br><span class=\"line\">26</span><br><span class=\"line\">27</span><br><span class=\"line\">28</span><br><span class=\"line\">29</span><br><span class=\"line\">30</span><br><span class=\"line\">31</span><br><span class=\"line\">32</span><br></pre></td><td class=\"code\"><pre><span class=\"line\"><span class=\"meta\">#<span class=\"meta-keyword\">include</span> <span class=\"meta-string\">&lt;bits/stdc++.h&gt;</span></span></span><br><span class=\"line\"><span class=\"keyword\">using</span> <span class=\"keyword\">namespace</span> <span class=\"built_in\">std</span>;</span><br><span class=\"line\"><span class=\"keyword\">const</span> <span class=\"keyword\">int</span> maxn = <span class=\"number\">1e6</span>+<span class=\"number\">7</span>;</span><br><span class=\"line\"><span class=\"keyword\">typedef</span> <span class=\"keyword\">long</span> <span class=\"keyword\">long</span> ll;</span><br><span class=\"line\"><span class=\"meta\">#<span class=\"meta-keyword\">define</span> clr(a,b) memset(a,b,sizeof(a))</span></span><br><span class=\"line\"><span class=\"keyword\">char</span> str[maxn];</span><br><span class=\"line\"><span class=\"keyword\">int</span> vis[<span class=\"number\">27</span>];</span><br><span class=\"line\"><span class=\"function\"><span class=\"keyword\">int</span> <span class=\"title\">main</span><span class=\"params\">()</span> </span>&#123;</span><br><span class=\"line\">    <span class=\"keyword\">int</span> t;</span><br><span class=\"line\">    <span class=\"built_in\">scanf</span>(<span class=\"string\">\"%d\"</span>, &amp;t);</span><br><span class=\"line\">    <span class=\"keyword\">while</span> (t--) &#123;</span><br><span class=\"line\">        clr(vis, <span class=\"number\">0</span>);</span><br><span class=\"line\">        <span class=\"keyword\">int</span> k; <span class=\"built_in\">scanf</span>(<span class=\"string\">\"%s %d\"</span>, str, &amp;k);</span><br><span class=\"line\">        <span class=\"keyword\">int</span> len = <span class=\"built_in\">strlen</span>(str);</span><br><span class=\"line\">        ll ans = <span class=\"number\">0</span>;</span><br><span class=\"line\">        <span class=\"keyword\">int</span> l = <span class=\"number\">0</span>, r = <span class=\"number\">0</span>;</span><br><span class=\"line\">        <span class=\"keyword\">int</span> sum = <span class=\"number\">0</span>;</span><br><span class=\"line\">        <span class=\"keyword\">for</span> (;;) &#123;</span><br><span class=\"line\">            <span class=\"keyword\">while</span> (r &lt; len &amp;&amp; sum &lt; k) &#123;</span><br><span class=\"line\">                <span class=\"keyword\">int</span> cur = str[r++] - <span class=\"string\">'a'</span>;</span><br><span class=\"line\">                <span class=\"keyword\">if</span> (!vis[cur]) sum++;</span><br><span class=\"line\">                vis[cur]++;</span><br><span class=\"line\">            &#125;</span><br><span class=\"line\">            <span class=\"keyword\">if</span> (sum &lt; k) <span class=\"keyword\">break</span>; <span class=\"comment\">//从某个左端点取遍也不足k个相异字符,推出</span></span><br><span class=\"line\">            ans += len - (r - <span class=\"number\">1</span>);<span class=\"comment\">// 此处r++后减掉但因为0-base不用再+1</span></span><br><span class=\"line\">            <span class=\"keyword\">int</span> cur = str[l++] - <span class=\"string\">'a'</span>;</span><br><span class=\"line\">            vis[cur]--;</span><br><span class=\"line\">            <span class=\"keyword\">if</span> (!vis[cur]) sum--;</span><br><span class=\"line\">        &#125;</span><br><span class=\"line\">        <span class=\"built_in\">printf</span>(<span class=\"string\">\"%lld\\n\"</span>, ans);</span><br><span class=\"line\">    &#125;</span><br><span class=\"line\">&#125;</span><br></pre></td></tr></table></figure>\n<h1 id=\"POJ-3320-Jessica’s-Reading-Problem\"><a href=\"#POJ-3320-Jessica’s-Reading-Problem\" class=\"headerlink\" title=\"POJ 3320 Jessica’s Reading Problem\"></a>POJ 3320 Jessica’s Reading Problem</h1><h2 id=\"题意-2\"><a href=\"#题意-2\" class=\"headerlink\" title=\"题意\"></a>题意</h2><p>给出$P(1e6)$页书，每页包含一个知识点，求一段长度最小的连续的区间使得包含所有的知识点。</p>\n<h2 id=\"trick-2\"><a href=\"#trick-2\" class=\"headerlink\" title=\"trick\"></a>trick</h2><p><code>尺取+map映射+set</code>，$O(n)$，细节看代码</p>\n<h2 id=\"code-2\"><a href=\"#code-2\" class=\"headerlink\" title=\"code\"></a>code</h2><figure class=\"highlight cpp\"><table><tr><td class=\"gutter\"><pre><span class=\"line\">1</span><br><span class=\"line\">2</span><br><span class=\"line\">3</span><br><span class=\"line\">4</span><br><span class=\"line\">5</span><br><span class=\"line\">6</span><br><span class=\"line\">7</span><br><span class=\"line\">8</span><br><span class=\"line\">9</span><br><span class=\"line\">10</span><br><span class=\"line\">11</span><br><span class=\"line\">12</span><br><span class=\"line\">13</span><br><span class=\"line\">14</span><br><span class=\"line\">15</span><br><span class=\"line\">16</span><br><span class=\"line\">17</span><br><span class=\"line\">18</span><br><span class=\"line\">19</span><br><span class=\"line\">20</span><br><span class=\"line\">21</span><br><span class=\"line\">22</span><br><span class=\"line\">23</span><br><span class=\"line\">24</span><br><span class=\"line\">25</span><br></pre></td><td class=\"code\"><pre><span class=\"line\"><span class=\"meta\">#<span class=\"meta-keyword\">include</span><span class=\"meta-string\">&lt;bits/stdc++.h&gt;</span></span></span><br><span class=\"line\"><span class=\"keyword\">using</span> <span class=\"keyword\">namespace</span> <span class=\"built_in\">std</span>;</span><br><span class=\"line\"><span class=\"keyword\">const</span> <span class=\"keyword\">int</span> maxn = <span class=\"number\">1e6</span>+<span class=\"number\">7</span>;</span><br><span class=\"line\"><span class=\"keyword\">int</span> a[maxn];</span><br><span class=\"line\"><span class=\"function\"><span class=\"keyword\">int</span> <span class=\"title\">main</span><span class=\"params\">()</span> </span>&#123;</span><br><span class=\"line\">    <span class=\"keyword\">int</span> p;<span class=\"built_in\">scanf</span>(<span class=\"string\">\"%d\"</span>,&amp;p);</span><br><span class=\"line\">    <span class=\"built_in\">set</span>&lt;<span class=\"keyword\">int</span>&gt; all;</span><br><span class=\"line\">    <span class=\"keyword\">for</span>(<span class=\"keyword\">int</span> i=<span class=\"number\">0</span>;i&lt;p;i++) &#123;</span><br><span class=\"line\">        <span class=\"built_in\">scanf</span>(<span class=\"string\">\"%d\"</span>,&amp;a[i]);</span><br><span class=\"line\">        all.insert(a[i]);</span><br><span class=\"line\">    &#125;</span><br><span class=\"line\">    <span class=\"keyword\">int</span> n = all.size();</span><br><span class=\"line\">    <span class=\"built_in\">map</span>&lt;<span class=\"keyword\">int</span>,<span class=\"keyword\">int</span>&gt; cnt; <span class=\"comment\">//cnt[知识点]=次数</span></span><br><span class=\"line\">    <span class=\"keyword\">int</span> sum  = <span class=\"number\">0</span>;</span><br><span class=\"line\">    <span class=\"keyword\">int</span> l = <span class=\"number\">0</span>, r = <span class=\"number\">0</span>;</span><br><span class=\"line\">    <span class=\"keyword\">int</span> res = p;</span><br><span class=\"line\">    <span class=\"keyword\">for</span>(;;) &#123;</span><br><span class=\"line\">        <span class=\"keyword\">while</span>(sum &lt; n &amp;&amp; r &lt; p)</span><br><span class=\"line\">            <span class=\"keyword\">if</span>(!cnt[a[r++]]++) sum ++; <span class=\"comment\">//该知识点第一次出现</span></span><br><span class=\"line\">        <span class=\"keyword\">if</span>(sum &lt; n) <span class=\"keyword\">break</span>;</span><br><span class=\"line\">        res = min(res, r-l);</span><br><span class=\"line\">        <span class=\"keyword\">if</span>(!--cnt[a[l++]]) sum--; <span class=\"comment\">//右移1位导致该知识点不出现更新sum</span></span><br><span class=\"line\">    &#125;</span><br><span class=\"line\">    <span class=\"keyword\">return</span> !<span class=\"built_in\">printf</span>(<span class=\"string\">\"%d\\n\"</span>,res);</span><br><span class=\"line\">&#125;</span><br></pre></td></tr></table></figure>\n<h1 id=\"HDU-1937-Finding-Seats\"><a href=\"#HDU-1937-Finding-Seats\" class=\"headerlink\" title=\"HDU 1937 Finding Seats\"></a>HDU 1937 Finding Seats</h1><h2 id=\"题意-3\"><a href=\"#题意-3\" class=\"headerlink\" title=\"题意\"></a>题意</h2><p>题意给出平面图$R*C$，选择一个面积最小的子矩阵使得内部点(<code>.</code>)的个数大于等于$k$个</p>\n<h2 id=\"trick-3\"><a href=\"#trick-3\" class=\"headerlink\" title=\"trick\"></a>trick</h2><p>类似的历史信息再利用优化暴力，不妨打前缀和<code>cnt[i][j]</code>表示从(1,1)到(i,j)的矩形内部点大于等于k的个数<br>化为经典的尺取做法递进枚举 $O(n^3)$<br><img src=\"https://hexo-1253425814.cossh.myqcloud.com/HDU1937%E4%BA%8C%E7%BB%B4%E5%B0%BA%E5%8F%96%E5%9B%BE%E8%A7%A3.png\" alt=\"\"></p>\n<h2 id=\"code-3\"><a href=\"#code-3\" class=\"headerlink\" title=\"code\"></a>code</h2><figure class=\"highlight cpp\"><table><tr><td class=\"gutter\"><pre><span class=\"line\">1</span><br><span class=\"line\">2</span><br><span class=\"line\">3</span><br><span class=\"line\">4</span><br><span class=\"line\">5</span><br><span class=\"line\">6</span><br><span class=\"line\">7</span><br><span class=\"line\">8</span><br><span class=\"line\">9</span><br><span class=\"line\">10</span><br><span class=\"line\">11</span><br><span class=\"line\">12</span><br><span class=\"line\">13</span><br><span class=\"line\">14</span><br><span class=\"line\">15</span><br><span class=\"line\">16</span><br><span class=\"line\">17</span><br><span class=\"line\">18</span><br><span class=\"line\">19</span><br><span class=\"line\">20</span><br><span class=\"line\">21</span><br><span class=\"line\">22</span><br><span class=\"line\">23</span><br><span class=\"line\">24</span><br><span class=\"line\">25</span><br><span class=\"line\">26</span><br><span class=\"line\">27</span><br><span class=\"line\">28</span><br><span class=\"line\">29</span><br><span class=\"line\">30</span><br><span class=\"line\">31</span><br><span class=\"line\">32</span><br><span class=\"line\">33</span><br></pre></td><td class=\"code\"><pre><span class=\"line\"></span><br><span class=\"line\"><span class=\"meta\">#<span class=\"meta-keyword\">include</span> <span class=\"meta-string\">&lt;bits/stdc++.h&gt;</span></span></span><br><span class=\"line\"><span class=\"keyword\">using</span> <span class=\"keyword\">namespace</span> <span class=\"built_in\">std</span>;</span><br><span class=\"line\"><span class=\"keyword\">const</span> <span class=\"keyword\">int</span> maxn = <span class=\"number\">333</span>;</span><br><span class=\"line\"><span class=\"keyword\">int</span> mp[maxn][maxn], sum[maxn][maxn];</span><br><span class=\"line\"><span class=\"keyword\">char</span> str[maxn];</span><br><span class=\"line\"><span class=\"keyword\">const</span> <span class=\"keyword\">int</span> inf = <span class=\"number\">0x3f3f3f3f</span>;</span><br><span class=\"line\"><span class=\"function\"><span class=\"keyword\">int</span> <span class=\"title\">main</span><span class=\"params\">()</span> </span>&#123;</span><br><span class=\"line\">    <span class=\"keyword\">int</span> k, r, c;</span><br><span class=\"line\">    <span class=\"keyword\">while</span> (<span class=\"built_in\">scanf</span>(<span class=\"string\">\"%d%d%d\"</span>, &amp;r, &amp;c, &amp;k) != EOF&amp;&amp;r+c+k) &#123;</span><br><span class=\"line\">        <span class=\"built_in\">memset</span>(sum, <span class=\"number\">0</span>, <span class=\"keyword\">sizeof</span>(sum));</span><br><span class=\"line\">        <span class=\"keyword\">for</span> (<span class=\"keyword\">int</span> i = <span class=\"number\">1</span>; i &lt;= r; i++) &#123;</span><br><span class=\"line\">            <span class=\"built_in\">scanf</span>(<span class=\"string\">\"%s\"</span>, str + <span class=\"number\">1</span>);</span><br><span class=\"line\">            <span class=\"keyword\">for</span> (<span class=\"keyword\">int</span> j = <span class=\"number\">1</span>; j &lt;= c; j++) &#123;</span><br><span class=\"line\">                mp[i][j] = str[j] == <span class=\"string\">'.'</span>;</span><br><span class=\"line\">                sum[i][j] += sum[i][j - <span class=\"number\">1</span>] + mp[i][j];</span><br><span class=\"line\">            &#125;</span><br><span class=\"line\">        &#125;</span><br><span class=\"line\">        <span class=\"keyword\">for</span> (<span class=\"keyword\">int</span> i = <span class=\"number\">2</span>; i &lt;= r; i++)</span><br><span class=\"line\">            <span class=\"keyword\">for</span> (<span class=\"keyword\">int</span> j = <span class=\"number\">1</span>; j &lt;= c; j++)</span><br><span class=\"line\">                sum[i][j] += sum[i - <span class=\"number\">1</span>][j]; <span class=\"comment\">//打完前缀和</span></span><br><span class=\"line\">        <span class=\"keyword\">int</span> ans = inf;</span><br><span class=\"line\">        <span class=\"keyword\">for</span> (<span class=\"keyword\">int</span> i = <span class=\"number\">1</span>; i &lt;= c; i++)</span><br><span class=\"line\">            <span class=\"keyword\">for</span> (<span class=\"keyword\">int</span> j = i; j &lt;= c; j++) &#123;<span class=\"comment\">// 枚举第i列到第j列</span></span><br><span class=\"line\">                <span class=\"keyword\">int</span> p = <span class=\"number\">1</span>; <span class=\"comment\">//行游标</span></span><br><span class=\"line\">                <span class=\"keyword\">for</span> (<span class=\"keyword\">int</span> t = p; t &lt;= r; t++) &#123;</span><br><span class=\"line\">                    <span class=\"keyword\">while</span>(sum[t][j]-sum[t][i<span class=\"number\">-1</span>]-sum[p<span class=\"number\">-1</span>][j]+sum[p<span class=\"number\">-1</span>][i<span class=\"number\">-1</span>]&gt;=k)</span><br><span class=\"line\">                        ans = min(ans, (j - i + <span class=\"number\">1</span>) * (t - p + <span class=\"number\">1</span>)), p++;</span><br><span class=\"line\">                &#125;</span><br><span class=\"line\">            &#125;</span><br><span class=\"line\">        <span class=\"built_in\">printf</span>(<span class=\"string\">\"%d\\n\"</span>,ans);</span><br><span class=\"line\">    &#125;</span><br><span class=\"line\">&#125;</span><br></pre></td></tr></table></figure>\n<h1 id=\"HDU-6103-Kirinriki\"><a href=\"#HDU-6103-Kirinriki\" class=\"headerlink\" title=\"HDU 6103 Kirinriki\"></a>HDU 6103 Kirinriki</h1><h2 id=\"题意-4\"><a href=\"#题意-4\" class=\"headerlink\" title=\"题意\"></a>题意</h2><p>定义长度相同的两字符串<code>A,B</code>,$dis_{A,B} = \\sum\\limits_{i=0}^{n-1}|A_{i}-B_{n-1-i}|$<br>问在给定字符串<code>S</code>下求长度最小的两个不重叠子串使得<code>dis</code>小于等于<code>m</code><br>多校第<code>6</code>场给队友写的，一顿操作过，好像是<code>暴力枚举+优化</code></p>\n<h2 id=\"trick-4\"><a href=\"#trick-4\" class=\"headerlink\" title=\"trick\"></a>trick</h2><p>这里用的尺取也是暴力枚举中心点的思想<br>大概的尺取过程，右边就不画了<br><img src=\"https://hexo-1253425814.cossh.myqcloud.com/HDU6102%E5%B0%BA%E5%8F%96%E6%B3%95%E8%AF%B4%E6%98%8E%E5%9B%BE.png\" width=\"50%\" height=\"50%\"></p>\n<h2 id=\"code-4\"><a href=\"#code-4\" class=\"headerlink\" title=\"code\"></a>code</h2><figure class=\"highlight cpp\"><table><tr><td class=\"gutter\"><pre><span class=\"line\">1</span><br><span class=\"line\">2</span><br><span class=\"line\">3</span><br><span class=\"line\">4</span><br><span class=\"line\">5</span><br><span class=\"line\">6</span><br><span class=\"line\">7</span><br><span class=\"line\">8</span><br><span class=\"line\">9</span><br><span class=\"line\">10</span><br><span class=\"line\">11</span><br><span class=\"line\">12</span><br><span class=\"line\">13</span><br><span class=\"line\">14</span><br><span class=\"line\">15</span><br><span class=\"line\">16</span><br><span class=\"line\">17</span><br><span class=\"line\">18</span><br><span class=\"line\">19</span><br><span class=\"line\">20</span><br><span class=\"line\">21</span><br><span class=\"line\">22</span><br><span class=\"line\">23</span><br><span class=\"line\">24</span><br><span class=\"line\">25</span><br><span class=\"line\">26</span><br><span class=\"line\">27</span><br><span class=\"line\">28</span><br><span class=\"line\">29</span><br><span class=\"line\">30</span><br><span class=\"line\">31</span><br><span class=\"line\">32</span><br><span class=\"line\">33</span><br><span class=\"line\">34</span><br><span class=\"line\">35</span><br><span class=\"line\">36</span><br><span class=\"line\">37</span><br></pre></td><td class=\"code\"><pre><span class=\"line\"><span class=\"meta\">#<span class=\"meta-keyword\">include</span> <span class=\"meta-string\">&lt;bits/stdc++.h&gt;</span></span></span><br><span class=\"line\"><span class=\"keyword\">using</span> <span class=\"keyword\">namespace</span> <span class=\"built_in\">std</span>;</span><br><span class=\"line\"><span class=\"keyword\">const</span> <span class=\"keyword\">int</span> maxn = <span class=\"number\">5005</span>;</span><br><span class=\"line\"><span class=\"keyword\">char</span> str[maxn];</span><br><span class=\"line\"><span class=\"keyword\">int</span> ans;</span><br><span class=\"line\"><span class=\"function\"><span class=\"keyword\">void</span> <span class=\"title\">solve</span><span class=\"params\">(<span class=\"keyword\">int</span> len, <span class=\"keyword\">int</span> limit)</span> </span>&#123;</span><br><span class=\"line\">    <span class=\"keyword\">for</span> (<span class=\"keyword\">int</span> i = <span class=\"number\">2</span>; i &lt;= len; i++) &#123;</span><br><span class=\"line\">        <span class=\"comment\">//遍历右端点，取等号便于处理奇偶mid</span></span><br><span class=\"line\">        <span class=\"keyword\">int</span> mid = (i &gt;&gt; <span class=\"number\">1</span>);</span><br><span class=\"line\">        <span class=\"keyword\">int</span> l = <span class=\"number\">0</span>, r = <span class=\"number\">0</span>;</span><br><span class=\"line\">        <span class=\"keyword\">int</span> sum = <span class=\"number\">0</span>;</span><br><span class=\"line\">        <span class=\"keyword\">for</span> (<span class=\"keyword\">int</span> j = <span class=\"number\">0</span>; j &lt; mid; j++) &#123;<span class=\"comment\">//遍历左端点</span></span><br><span class=\"line\">            sum += <span class=\"built_in\">abs</span>(str[j] - str[i - j - <span class=\"number\">1</span>]);</span><br><span class=\"line\">            <span class=\"keyword\">if</span> (sum &lt;= limit)</span><br><span class=\"line\">                r++, ans = max(ans, r);</span><br><span class=\"line\">            <span class=\"keyword\">else</span> &#123; <span class=\"comment\">//相同长度平移</span></span><br><span class=\"line\">                r--;</span><br><span class=\"line\">                sum -= <span class=\"built_in\">abs</span>(str[j] - str[i - j - <span class=\"number\">1</span>]); <span class=\"comment\">//还原状态 减掉当前的j</span></span><br><span class=\"line\">                sum -= <span class=\"built_in\">abs</span>(str[l] - str[i - l - <span class=\"number\">1</span>]);<span class=\"comment\">// 减去当前的l</span></span><br><span class=\"line\">                l++, j--; <span class=\"comment\">//移动左端点，下一时刻相当于平移</span></span><br><span class=\"line\">            &#125;</span><br><span class=\"line\">        &#125;</span><br><span class=\"line\">    &#125;</span><br><span class=\"line\">&#125;</span><br><span class=\"line\"><span class=\"function\"><span class=\"keyword\">int</span> <span class=\"title\">main</span><span class=\"params\">()</span> </span>&#123;</span><br><span class=\"line\">    <span class=\"keyword\">int</span> t;</span><br><span class=\"line\">    <span class=\"built_in\">scanf</span>(<span class=\"string\">\"%d\"</span>, &amp;t);</span><br><span class=\"line\">    <span class=\"keyword\">while</span> (t--) &#123;</span><br><span class=\"line\">        <span class=\"keyword\">int</span> m; <span class=\"built_in\">scanf</span>(<span class=\"string\">\"%d %s\"</span>, &amp;m, str);</span><br><span class=\"line\">        ans = <span class=\"number\">0</span>;</span><br><span class=\"line\">        <span class=\"keyword\">int</span> len = <span class=\"built_in\">strlen</span>(str);</span><br><span class=\"line\">        solve(len, m);</span><br><span class=\"line\">        strrev(str); <span class=\"comment\">//正反各跑一遍</span></span><br><span class=\"line\">        solve(len, m);</span><br><span class=\"line\">        <span class=\"built_in\">printf</span>(<span class=\"string\">\"%d\\n\"</span>, ans);</span><br><span class=\"line\">    &#125;</span><br><span class=\"line\">&#125;</span><br></pre></td></tr></table></figure>\n<blockquote>\n<p>犹疑<br>天空深处孤寂依然<br>给你满天的星<br>和说着星的<br>一百种理由<br>使你凝视</p>\n</blockquote>\n","prev":{"title":"HDU 6253 knightmare 2017CCPC-K","slug":"2018-02-01-hdu 6253 knightmare"},"next":{"title":"Atcoder 88 D-Wide Flip","slug":"2018-01-02-adcoder 88 D"},"link":"/post/2018-01-08-尺取法小结","toc":[{"title":"POJ 3061 Sequence","id":"POJ-3061-Sequence","index":"1","children":[{"title":"题意","id":"题意","index":"1.1"},{"title":"trick","id":"trick","index":"1.2"},{"title":"code","id":"code","index":"1.3"}]},{"title":"HDU 5672 String","id":"HDU-5672-String","index":"2","children":[{"title":"题意","id":"题意-1","index":"2.1"},{"title":"trick","id":"trick-1","index":"2.2"},{"title":"code","id":"code-1","index":"2.3"}]},{"title":"POJ 3320 Jessica’s Reading Problem","id":"POJ-3320-Jessica’s-Reading-Problem","index":"3","children":[{"title":"题意","id":"题意-2","index":"3.1"},{"title":"trick","id":"trick-2","index":"3.2"},{"title":"code","id":"code-2","index":"3.3"}]},{"title":"HDU 1937 Finding Seats","id":"HDU-1937-Finding-Seats","index":"4","children":[{"title":"题意","id":"题意-3","index":"4.1"},{"title":"trick","id":"trick-3","index":"4.2"},{"title":"code","id":"code-3","index":"4.3"}]},{"title":"HDU 6103 Kirinriki","id":"HDU-6103-Kirinriki","index":"5","children":[{"title":"题意","id":"题意-4","index":"5.1"},{"title":"trick","id":"trick-4","index":"5.2"},{"title":"code","id":"code-4","index":"5.3"}]}]}